motor_bundle/__init__.py
motor_bundle/bundle.py
motor_bundle-2.0.0.dist-info/LICENSE
motor_bundle-2.0.0.dist-info/WHEEL
motor_bundle-2.0.0.dist-info/METADATA
motor_bundle-2.0.0.dist-info/RECORD
